{
  "id": "One Last Time 赤西仁",
  "folderName": "One Last Time 赤西仁",
  "songName": "One Last Time",
  "artist": "赤西仁",
  "relationship": "恋人",
  "setting": "A couple is breaking up and one person is moving out of their shared apartment.",
  "speakerA": {
    "name": "Mark",
    "type": "男性",
    "voice": "CfDbY7v8tDkTvB9rNcUw"
  },
  "speakerB": {
    "name": "Chloe",
    "type": "女性",
    "voice": "cNYrMw9glwJZXR8RwbuR"
  },
  "videoId": "J5BmHcpRPRI",
  "thumbnailUrl": "https://img.youtube.com/vi/J5BmHcpRPRI/hqdefault.jpg",
  "lyrics": "I'm packing my bags 'cuz the journey is over\nAnd we were never good enough for each other\nYou put me through hell every time that I tried\nTonight I'm gonna make you pay one last time\n\nYou ain't gotta be shy I want the neighbors to hear it\nThe way we used to do it in the beginning\nSo take your time\nI'm waiting at the door\nAnd imma do it do it do it do it do it 'til you want more\n\n(Temperature's gettin' hot don't fight it)\nI don't give a damn what you say you gotta do baby\n(Kiss ya lips so soft then bite it)\n\nWhen I'm through you gon' wish\nthat you never would have gave me up\n\nI'm packing my bags 'cuz the journey is over\nAnd we were never good enough for each other\nYou put me through hell every time that I tried\nTonight I'm gonna make you pay one last time\n\nRemember back in the day I said nobody was better\nAnd I was gonna change your life forever\nYou took me for granted\nThought it was a game\nYou 'bout to get it so good\nthat your next man will know my name\n\n(Let your hair down baby turn the lights off)\nGrab a life vest we're sailing into ecstacy\n\n(Don't hold back baby just shout out)\nIt's the last time you gonna have a man\ngive it to you like me\n\nI'm packing my bags 'cuz the journey is over\nAnd we were never good enough for each other\nYou put me through hell every time that I tried\nTonight I'm gonna make you pay one last time\n\nI'm packing my bags 'cuz the journey is over\nAnd we were never good enough for each other\nYou put me through hell every time that I tried\nTonight I'm gonna make you pay one last time",
  "lyricsJa": [
    {
      "en": "I'm packing my bags 'cuz the journey is over",
      "ja": "荷物をまとめてる　旅は終わったから"
    },
    {
      "en": "And we were never good enough for each other",
      "ja": "僕たちは決して　お似合いの二人じゃなかった"
    },
    {
      "en": "You put me through hell every time that I tried",
      "ja": "僕が努力するたびに　君は僕を地獄に突き落とした"
    },
    {
      "en": "Tonight I'm gonna make you pay one last time",
      "ja": "今夜　最後にもう一度　君に報いを受けさせてやる"
    },
    {
      "en": "",
      "ja": ""
    },
    {
      "en": "You ain't gotta be shy I want the neighbors to hear it",
      "ja": "恥ずかしがらなくていい　近所中に聞こえるくらいがいいんだ"
    },
    {
      "en": "The way we used to do it in the beginning",
      "ja": "付き合い始めた頃　僕たちがしていたみたいに"
    },
    {
      "en": "So take your time",
      "ja": "だからゆっくり時間をかけて"
    },
    {
      "en": "I'm waiting at the door",
      "ja": "ドアの前で待っているよ"
    },
    {
      "en": "And imma do it do it do it do it do it 'til you want more",
      "ja": "君がもっと欲しがるまで　何度も何度もしてあげる"
    },
    {
      "en": "",
      "ja": ""
    },
    {
      "en": "(Temperature's gettin' hot don't fight it)",
      "ja": "（熱くなってきた　抗わないで）"
    },
    {
      "en": "I don't give a damn what you say you gotta do baby",
      "ja": "君がこれから何をすべきなんて　知ったこっちゃないよ"
    },
    {
      "en": "(Kiss ya lips so soft then bite it)",
      "ja": "（唇に優しくキスして　それから噛んで）"
    },
    {
      "en": "",
      "ja": ""
    },
    {
      "en": "When I'm through you gon' wish",
      "ja": "僕がやり終える頃には　君はこう願うだろう"
    },
    {
      "en": "that you never would have gave me up",
      "ja": "僕を手放さなきゃよかったって"
    },
    {
      "en": "",
      "ja": ""
    },
    {
      "en": "I'm packing my bags 'cuz the journey is over",
      "ja": "荷物をまとめてる　旅は終わったから"
    },
    {
      "en": "And we were never good enough for each other",
      "ja": "僕たちは決して　お似合いの二人じゃなかった"
    },
    {
      "en": "You put me through hell every time that I tried",
      "ja": "僕が努力するたびに　君は僕を地獄に突き落とした"
    },
    {
      "en": "Tonight I'm gonna make you pay one last time",
      "ja": "今夜　最後にもう一度　君に報いを受けさせてやる"
    },
    {
      "en": "",
      "ja": ""
    },
    {
      "en": "Remember back in the day I said nobody was better",
      "ja": "昔　君以上の人はいないって言ったのを覚えてる？"
    },
    {
      "en": "And I was gonna change your life forever",
      "ja": "君の人生を永遠に変えてあげようとしてたんだ"
    },
    {
      "en": "You took me for granted",
      "ja": "君は僕の存在を当たり前だと思って"
    },
    {
      "en": "Thought it was a game",
      "ja": "ただの遊びだと思ってたんだろう"
    },
    {
      "en": "You 'bout to get it so good",
      "ja": "これから君を最高にいい気分にさせてやる"
    },
    {
      "en": "that your next man will know my name",
      "ja": "次の男が僕の名前を知ることになるくらいに"
    },
    {
      "en": "",
      "ja": ""
    },
    {
      "en": "(Let your hair down baby turn the lights off)",
      "ja": "（髪をほどいて　明かりを消して）"
    },
    {
      "en": "Grab a life vest we're sailing into ecstacy",
      "ja": "救命胴衣を掴んで　エクスタシーへと漕ぎ出そう"
    },
    {
      "en": "",
      "ja": ""
    },
    {
      "en": "(Don't hold back baby just shout out)",
      "ja": "（我慢しないで　ただ叫んで）"
    },
    {
      "en": "It's the last time you gonna have a man",
      "ja": "僕のような男が君をこんな風に愛してあげるのは"
    },
    {
      "en": "give it to you like me",
      "ja": "これで最後になるんだから"
    },
    {
      "en": "",
      "ja": ""
    },
    {
      "en": "I'm packing my bags 'cuz the journey is over",
      "ja": "荷物をまとめてる　旅は終わったから"
    },
    {
      "en": "And we were never good enough for each other",
      "ja": "僕たちは決して　お似合いの二人じゃなかった"
    },
    {
      "en": "You put me through hell every time that I tried",
      "ja": "僕が努力するたびに　君は僕を地獄に突き落とした"
    },
    {
      "en": "Tonight I'm gonna make you pay one last time",
      "ja": "今夜　最後にもう一度　君に報いを受けさせてやる"
    },
    {
      "en": "",
      "ja": ""
    },
    {
      "en": "I'm packing my bags 'cuz the journey is over",
      "ja": "荷物をまとめてる　旅は終わったから"
    },
    {
      "en": "And we were never good enough for each other",
      "ja": "僕たちは決して　お似合いの二人じゃなかった"
    },
    {
      "en": "You put me through hell every time that I tried",
      "ja": "僕が努力するたびに　君は僕を地獄に突き落とした"
    },
    {
      "en": "Tonight I'm gonna make you pay one last time",
      "ja": "今夜、最後にもう一度だけ、君に思い知らせてやるよ"
    }
  ],
  "conversation": [
    {
      "speaker": "A",
      "speakerName": "Mark",
      "speakerType": "男性",
      "sentences": [
        {
          "text": "I've finally finished packing my bags.",
          "displayHtml": "I've finally finished <span class=\"lyric-phrase\">packing my bags</span>.",
          "audio": "/songs/One%20Last%20Time%20%E8%B5%A4%E8%A5%BF%E4%BB%81/0_0.mp3"
        },
        {
          "text": "I guess our journey is officially over.",
          "displayHtml": "I guess our <span class=\"lyric-word\">journey</span> is officially over.",
          "audio": "/songs/One%20Last%20Time%20%E8%B5%A4%E8%A5%BF%E4%BB%81/0_1.mp3"
        }
      ],
      "japanese": "ようやく荷造りが終わったよ。僕たちの旅も、これで本当におしまいだね。"
    },
    {
      "speaker": "B",
      "speakerName": "Chloe",
      "speakerType": "女性",
      "sentences": [
        {
          "text": "I can't believe it's actually happening.",
          "displayHtml": "I can't believe it's actually happening.",
          "audio": "/songs/One%20Last%20Time%20%E8%B5%A4%E8%A5%BF%E4%BB%81/1_0.mp3"
        },
        {
          "text": "Did you really have to say we were never good enough for each other?",
          "displayHtml": "Did you really have to say we <span class=\"lyric-phrase\">were never good enough</span> for each other?",
          "audio": "/songs/One%20Last%20Time%20%E8%B5%A4%E8%A5%BF%E4%BB%81/1_1.mp3"
        }
      ],
      "japanese": "本当に終わっちゃうなんて信じられない。「お互いにふさわしくなかった」なんて、本気で思ってるの？"
    },
    {
      "speaker": "A",
      "speakerName": "Mark",
      "speakerType": "男性",
      "sentences": [
        {
          "text": "Look, I'm just being honest.",
          "displayHtml": "Look, I'm just being honest.",
          "audio": "/songs/One%20Last%20Time%20%E8%B5%A4%E8%A5%BF%E4%BB%81/2_0.mp3"
        },
        {
          "text": "You took me for granted for way too long.",
          "displayHtml": "You <span class=\"lyric-phrase\">took me for granted</span> for way too long.",
          "audio": "/songs/One%20Last%20Time%20%E8%B5%A4%E8%A5%BF%E4%BB%81/2_1.mp3"
        }
      ],
      "japanese": "正直に言ってるだけだよ。君はあまりに長い間、僕のことをないがしろにしていたから。"
    },
    {
      "speaker": "B",
      "speakerName": "Chloe",
      "speakerType": "女性",
      "sentences": [
        {
          "text": "Maybe I did, but you put me through hell sometimes, too.",
          "displayHtml": "Maybe I did, but you <span class=\"lyric-phrase\">put me through hell</span> sometimes, too.",
          "audio": "/songs/One%20Last%20Time%20%E8%B5%A4%E8%A5%BF%E4%BB%81/3_0.mp3"
        },
        {
          "text": "It wasn't always easy for me.",
          "displayHtml": "It wasn't always easy for me.",
          "audio": "/songs/One%20Last%20Time%20%E8%B5%A4%E8%A5%BF%E4%BB%81/3_1.mp3"
        }
      ],
      "japanese": "そうだったかもしれないけど、あなただって私にひどい思いをさせたじゃない。私だって楽じゃなかったわ。"
    },
    {
      "speaker": "A",
      "speakerName": "Mark",
      "speakerType": "男性",
      "sentences": [
        {
          "text": "I know.",
          "displayHtml": "I know.",
          "audio": "/songs/One%20Last%20Time%20%E8%B5%A4%E8%A5%BF%E4%BB%81/4_0.mp3"
        },
        {
          "text": "Anyway, just take your time getting the rest of your things.",
          "displayHtml": "Anyway, just <span class=\"lyric-phrase\">take your time</span> getting the rest of your things.",
          "audio": "/songs/One%20Last%20Time%20%E8%B5%A4%E8%A5%BF%E4%BB%81/4_1.mp3"
        }
      ],
      "japanese": "分かってる。とにかく、残りの荷物はゆっくり片付けていいから。"
    },
    {
      "speaker": "B",
      "speakerName": "Chloe",
      "speakerType": "女性",
      "sentences": [
        {
          "text": "Thanks.",
          "displayHtml": "Thanks.",
          "audio": "/songs/One%20Last%20Time%20%E8%B5%A4%E8%A5%BF%E4%BB%81/5_0.mp3"
        },
        {
          "text": "I'm just waiting at the door for my ride to arrive.",
          "displayHtml": "I'm just <span class=\"lyric-phrase\">waiting at the door</span> for my ride to arrive.",
          "audio": "/songs/One%20Last%20Time%20%E8%B5%A4%E8%A5%BF%E4%BB%81/5_1.mp3"
        }
      ],
      "japanese": "ありがとう。迎えの車が来るのを、玄関で待ってるわ。"
    },
    {
      "speaker": "A",
      "speakerName": "Mark",
      "speakerType": "男性",
      "sentences": [
        {
          "text": "No rush.",
          "displayHtml": "No rush.",
          "audio": "/songs/One%20Last%20Time%20%E8%B5%A4%E8%A5%BF%E4%BB%81/6_0.mp3"
        },
        {
          "text": "I'll always remember how things were back in the day.",
          "displayHtml": "I'll always remember how things were <span class=\"lyric-phrase\">back in the day</span>.",
          "audio": "/songs/One%20Last%20Time%20%E8%B5%A4%E8%A5%BF%E4%BB%81/6_1.mp3"
        }
      ],
      "japanese": "急がなくていいよ。昔の楽しかった時のことは、ずっと覚えてるから。"
    },
    {
      "speaker": "B",
      "speakerName": "Chloe",
      "speakerType": "女性",
      "sentences": [
        {
          "text": "Me too.",
          "displayHtml": "Me too.",
          "audio": "/songs/One%20Last%20Time%20%E8%B5%A4%E8%A5%BF%E4%BB%81/7_0.mp3"
        },
        {
          "text": "I really thought we could change things, but I guess it's too late.",
          "displayHtml": "I really thought we could <span class=\"lyric-word\">change</span> things, but I guess it's too late.",
          "audio": "/songs/One%20Last%20Time%20%E8%B5%A4%E8%A5%BF%E4%BB%81/7_1.mp3"
        }
      ],
      "japanese": "私もよ。何かを変えられるって信じてたけど、もう手遅れみたいね。"
    }
  ],
  "createdAt": "2026-03-30T15:41:28.011Z"
}
